Workbook
Name stock_name: 'Raw Data'!$B$2:$B$701
Name ticker: 'Raw Data'!$C$2:$C$701

Sheet Portfolio
A1: sr-no | B1: company | C1: weight | D1: ticker | E1: normwt
A2: 1 | B2: ABBOTT INDIA LTD. | C2: 10 | D2: =IF(B2="", "", VLOOKUP(B2,'Raw Data'!$B$1:$C$701, 2, 0)) -> ABBOTINDIA.NS | E2: =IF(B2="","",C2/$C$52) -> 0.027027027
A3: =IF(B3="","",A2+1) -> 2 | B3: V.I.P.INDUSTRIES LTD. | C3: 10 | D3: =IF(B3="", "", VLOOKUP(B3,'Raw Data'!$B$1:$C$701, 2, 0)) -> VIPIND.NS | E3: =IF(B3="","",C3/$C$52) -> 0.027027027
A4: =IF(B4="","",A3+1) -> 3 | B4: AMBUJA CEMENTS LTD. | C4: 10 | D4: =IF(B4="", "", VLOOKUP(B4,'Raw Data'!$B$1:$C$701, 2, 0)) -> AMBUJACEM.NS | E4: =IF(B4="","",C4/$C$52) -> 0.027027027
A5: =IF(B5="","",A4+1) -> 4 | B5: ASHOK LEYLAND LTD. | C5: 10 | D5: =IF(B5="", "", VLOOKUP(B5,'Raw Data'!$B$1:$C$701, 2, 0)) -> ASHOKLEY.NS | E5: =IF(B5="","",C5/$C$52) -> 0.027027027
A6: =IF(B6="","",A5+1) -> 5 | B6: AVENUE SUPERMARTS LTD | C6: 10 | D6: =IF(B6="", "", VLOOKUP(B6,'Raw Data'!$B$1:$C$701, 2, 0)) -> DMART.NS | E6: =IF(B6="","",C6/$C$52) -> 0.027027027
A7: =IF(B7="","",A6+1) -> 6 | B7: BANDHAN BANK LTD | C7: 10 | D7: =IF(B7="", "", VLOOKUP(B7,'Raw Data'!$B$1:$C$701, 2, 0)) -> BANDHANBNK.NS | E7: =IF(B7="","",C7/$C$52) -> 0.027027027
A8: =IF(B8="","",A7+1) -> 7 | B8: BHARAT DYNAMICS LTD | C8: 10 | D8: =IF(B8="", "", VLOOKUP(B8,'Raw Data'!$B$1:$C$701, 2, 0)) -> BDL.NS | E8: =IF(B8="","",C8/$C$52) -> 0.027027027
A9: =IF(B9="","",A8+1) -> 8 | B9: BOMBAY DYEING & MFG.CO.LTD. | C9: 10 | D9: =IF(B9="", "", VLOOKUP(B9,'Raw Data'!$B$1:$C$701, 2, 0)) -> BOMDYEING.NS | E9: =IF(B9="","",C9/$C$52) -> 0.027027027
A10: =IF(B10="","",A9+1) -> 9 | B10: CCL PRODUCTS (INDIA) LTD. | C10: 10 | D10: =IF(B10="", "", VLOOKUP(B10,'Raw Data'!$B$1:$C$701, 2, 0)) -> CCL.NS | E10: =IF(B10="","",C10/$C$52) -> 0.027027027
A11: =IF(B11="","",A10+1) -> 10 | B11: CITY UNION BANK LTD. | C11: 10 | D11: =IF(B11="", "", VLOOKUP(B11,'Raw Data'!$B$1:$C$701, 2, 0)) -> CUB.NS | E11: =IF(B11="","",C11/$C$52) -> 0.027027027
A12: =IF(B12="","",A11+1) -> 11 | B12: CYIENT LIMITED | C12: 10 | D12: =IF(B12="", "", VLOOKUP(B12,'Raw Data'!$B$1:$C$701, 2, 0)) -> CYIENT.NS | E12: =IF(B12="","",C12/$C$52) -> 0.027027027
A13: =IF(B13="","",A12+1) -> 12 | B13: DILIP BUILDCON LTD | C13: 10 | D13: =IF(B13="", "", VLOOKUP(B13,'Raw Data'!$B$1:$C$701, 2, 0)) -> DBL.NS | E13: =IF(B13="","",C13/$C$52) -> 0.027027027
A14: =IF(B14="","",A13+1) -> 13 | B14: EICHER MOTORS LTD. | C14: 10 | D14: =IF(B14="", "", VLOOKUP(B14,'Raw Data'!$B$1:$C$701, 2, 0)) -> EICHERMOT.NS | E14: =IF(B14="","",C14/$C$52) -> 0.027027027
... A38: =IF(B38="","",A37+1) -> 37 | B38: STEEL AUTHORITY OF INDIA LTD. | C38: 10 | D38: =IF(B38="", "", VLOOKUP(B38,'Raw Data'!$B$1:$C$701, 2, 0)) -> SAIL.NS | E38: =IF(B38="","",C38/$C$52) -> 0.027027027
A39: =IF(B39="","",A38+1) | D39: =IF(B39="", "", VLOOKUP(B39,'Raw Data'!$B$1:$C$701, 2, 0)) | E39: =IF(B39="","",C39/$C$52)
A40: =IF(B40="","",A39+1) | D40: =IF(B40="", "", VLOOKUP(B40,'Raw Data'!$B$1:$C$701, 2, 0)) | E40: =IF(B40="","",C40/$C$52)
A41: =IF(B41="","",A40+1) | D41: =IF(B41="", "", VLOOKUP(B41,'Raw Data'!$B$1:$C$701, 2, 0)) | E41: =IF(B41="","",C41/$C$52)
A42: =IF(B42="","",A41+1) | D42: =IF(B42="", "", VLOOKUP(B42,'Raw Data'!$B$1:$C$701, 2, 0)) | E42: =IF(B42="","",C42/$C$52)
A43: =IF(B43="","",A42+1) | D43: =IF(B43="", "", VLOOKUP(B43,'Raw Data'!$B$1:$C$701, 2, 0)) | E43: =IF(B43="","",C43/$C$52)
A44: =IF(B44="","",A43+1) | D44: =IF(B44="", "", VLOOKUP(B44,'Raw Data'!$B$1:$C$701, 2, 0)) | E44: =IF(B44="","",C44/$C$52)
A45: =IF(B45="","",A44+1) | D45: =IF(B45="", "", VLOOKUP(B45,'Raw Data'!$B$1:$C$701, 2, 0)) | E45: =IF(B45="","",C45/$C$52)
A46: =IF(B46="","",A45+1) | D46: =IF(B46="", "", VLOOKUP(B46,'Raw Data'!$B$1:$C$701, 2, 0)) | E46: =IF(B46="","",C46/$C$52)
A47: =IF(B47="","",A46+1) | D47: =IF(B47="", "", VLOOKUP(B47,'Raw Data'!$B$1:$C$701, 2, 0)) | E47: =IF(B47="","",C47/$C$52)
A48: =IF(B48="","",A47+1) | D48: =IF(B48="", "", VLOOKUP(B48,'Raw Data'!$B$1:$C$701, 2, 0)) | E48: =IF(B48="","",C48/$C$52)
A49: =IF(B49="","",A48+1) | D49: =IF(B49="", "", VLOOKUP(B49,'Raw Data'!$B$1:$C$701, 2, 0)) | E49: =IF(B49="","",C49/$C$52)
A50: =IF(B50="","",A49+1) | D50: =IF(B50="", "", VLOOKUP(B50,'Raw Data'!$B$1:$C$701, 2, 0)) | E50: =IF(B50="","",C50/$C$52)
A51: =IF(B51="","",A50+1) | D51: =IF(B51="", "", VLOOKUP(B51,'Raw Data'!$B$1:$C$701, 2, 0)) | E51: =IF(B51="","",C51/$C$52)
A52: x | B52: x | C52: =SUM(C2:C51) -> 370 | D52: x | E52: =C52/$C$52 -> 1

Sheet Raw Data
A1: Sr. No | B1: Company Name | C1: Ticker
A2: 1 | B2: 3M INDIA LTD. | C2: 3MINDIA.NS | D2: 1 | F2: AJANTA PHARMA LTD. | H2: 71
A3: 2 | B3: AARTI DRUGS LTD. | C3: AARTIDRUGS.NS | D3: 2 | F3: ASIAN PAINTS LTD. | H3: 178
A4: 3 | B4: AARTI INDUSTRIES LTD. | C4: AARTIIND.NS | D4: 3 | F4: BANDHAN BANK LTD | H4: 203
A5: 4 | B5: AAVAS FINANCIERS LTD | C5: AAVAS.NS | D5: 4 | F5: BLUE DART EXPRESS LTD. | H5: 33
A6: 5 | B6: ABB INDIA LIMITED | C6: ABB.NS | D6: 5 | F6: CADILA HEALTHCARE LTD. | H6: 109
A7: 6 | B7: ABB POWER PRODUCTS AND SYSTEMS INDIA LTD | C7: POWERINDIA.NS | D7: 6 | F7: CASTROL INDIA LTD. | H7: 116
A8: 7 | B8: ABBOTT INDIA LTD. | C8: ABBOTINDIA.NS | D8: 7 | F8: CRISIL LTD. | H8: 145
A9: 8 | B9: ACC LTD. | C9: ACC.NS | D9: 8 | F9: DIVI'S LABORATORIES LTD. | H9: 284
A10: 9 | B10: ACCELYA SOLUTIONS INDIA LTD | C10: ACCELYA.NS | D10: 9 | F10: DR. LAL PATHLABS LTD | H10: 224
A11: 10 | B11: ACTION CONSTRUCTION EQUIPMENT LTD. | C11: ACE.NS | D11: 10 | F11: EICHER MOTORS LTD. | H11: 68
A12: 11 | B12: ADANI ENTERPRISES LTD. | C12: ADANIENT.NS | D12: 11 | F12: HCL TECHNOLOGIES LTD. | H12: 153
A13: 12 | B13: ADANI GREEN ENERGY LTD | C13: ADANIGREEN.NS | D13: 12 | F13: HDFC BANK LTD | H13: 285
... A33: 32 | B33: ALLCARGO LOGISTICS LTD. | C33: ALLCARGO.NS | D33: 4 | F33: V-MART RETAIL LTD. | H33: 74
A34: 33 | B34: AMARA RAJA BATTERIES LTD. | C34: AMARAJABAT.NS | D34: 5
A35: 34 | B35: AMBER ENTERPRISES INDIA LTD | C35: AMBER.NS | D35: 6
A36: 35 | B36: AMBUJA CEMENTS LTD. | C36: AMBUJACEM.NS | D36: 7
A37: 36 | B37: APAR INDUSTRIES LTD. | C37: APARINDS.NS | D37: 8
A38: 37 | B38: APCOTEX INDUSTRIES LTD. | C38: APCOTEXIND.NS | D38: 9
A39: 38 | B39: APEX FROZEN FOODS LTD | C39: APEX.NS | D39: 10
A40: 39 | B40: APL APOLLO TUBES LTD. | C40: APLAPOLLO.NS | D40: 11
A41: 40 | B41: APOLLO HOSPITALS ENTERPRISE LTD. | C41: APOLLOHOSP.NS | D41: 12
A42: 41 | B42: APOLLO PIPES LTD | C42: APOLLOPIPES.NS | D42: 13
A43: 42 | B43: APOLLO TRICOAT TUBES LTD | C43: APOLLOTRI.NS | D43: 14
A44: 43 | B44: APOLLO TYRES LTD. | C44: APOLLOTYRE.NS | D44: 1
A45: 44 | B45: APTECH LTD. | C45: APTECHT.NS | D45: 2
... A701: 700 | B701: ZYDUS WELLNESS LTD. | C701: ZYDUSWELL.NS | D701: 14

Sheet Sheet1
A1: TATA CONSULTANCY SERVICES LTD.
A2: TATA CONSUMER PRODUCTS LTD
A3: TATA ELXSI LTD.
A4: TATA MOTORS LTD.
A5: TATA STEEL LTD.
A7: ADANI ENTERPRISES LTD.
A8: ADANI GREEN ENERGY LTD
A9: ADANI PORTS AND SPECIAL ECONOMIC ZONE LTD.
A10: ADANI POWER LTD.
A11: ADANI TOTAL GAS LTD
A12: ADANI TRANSMISSION LTD
A14: HDFC ASSET MANAGEMENT COMPANY LTD
... A29: BAJAJ FINSERV LTD.
