Workbook
Name stock_name: 'Raw Data'!$B$2:$B$701
Name ticker: 'Raw Data'!$C$2:$C$701

Sheet Portfolio
A1: sr-no | B1: company | C1: weight | D1: ticker | E1: normwt
A2: 1 | B2: AJANTA PHARMA LTD. | C2: 71 | D2: =IF(B2="", "", VLOOKUP(B2,'Raw Data'!$B$1:$C$701, 2, 0)) -> AJANTPHARM.NS | E2: =IF(B2="","",C2/$C$52) -> 0.014185814
A3: =IF(B3="","",A2+1) -> 2 | B3: ASIAN PAINTS LTD. | C3: 178 | D3: =IF(B3="", "", VLOOKUP(B3,'Raw Data'!$B$1:$C$701, 2, 0)) -> ASIANPAINT.NS | E3: =IF(B3="","",C3/$C$52) -> 0.035564436
A4: =IF(B4="","",A3+1) -> 3 | B4: BANDHAN BANK LTD | C4: 203 | D4: =IF(B4="", "", VLOOKUP(B4,'Raw Data'!$B$1:$C$701, 2, 0)) -> BANDHANBNK.NS | E4: =IF(B4="","",C4/$C$52) -> 0.040559441
A5: =IF(B5="","",A4+1) -> 4 | B5: BLUE DART EXPRESS LTD. | C5: 33 | D5: =IF(B5="", "", VLOOKUP(B5,'Raw Data'!$B$1:$C$701, 2, 0)) -> BLUEDART.NS | E5: =IF(B5="","",C5/$C$52) -> 0.0065934066
A6: =IF(B6="","",A5+1) -> 5 | B6: CADILA HEALTHCARE LTD. | C6: 109 | D6: =IF(B6="", "", VLOOKUP(B6,'Raw Data'!$B$1:$C$701, 2, 0)) -> CADILAHC.NS | E6: =IF(B6="","",C6/$C$52) -> 0.021778222
A7: =IF(B7="","",A6+1) -> 6 | B7: CASTROL INDIA LTD. | C7: 116 | D7: =IF(B7="", "", VLOOKUP(B7,'Raw Data'!$B$1:$C$701, 2, 0)) -> CASTROLIND.NS | E7: =IF(B7="","",C7/$C$52) -> 0.023176823
A8: =IF(B8="","",A7+1) -> 7 | B8: CRISIL LTD. | C8: 145 | D8: =IF(B8="", "", VLOOKUP(B8,'Raw Data'!$B$1:$C$701, 2, 0)) -> CRISIL.NS | E8: =IF(B8="","",C8/$C$52) -> 0.028971029
A9: =IF(B9="","",A8+1) -> 8 | B9: DIVI'S LABORATORIES LTD. | C9: 284 | D9: =IF(B9="", "", VLOOKUP(B9,'Raw Data'!$B$1:$C$701, 2, 0)) -> DIVISLAB.NS | E9: =IF(B9="","",C9/$C$52) -> 0.056743257
A10: =IF(B10="","",A9+1) -> 9 | B10: DR. LAL PATHLABS LTD | C10: 224 | D10: =IF(B10="", "", VLOOKUP(B10,'Raw Data'!$B$1:$C$701, 2, 0)) -> LALPATHLAB.NS | E10: =IF(B10="","",C10/$C$52) -> 0.044755245
A11: =IF(B11="","",A10+1) -> 10 | B11: EICHER MOTORS LTD. | C11: 68 | D11: =IF(B11="", "", VLOOKUP(B11,'Raw Data'!$B$1:$C$701, 2, 0)) -> EICHERMOT.NS | E11: =IF(B11="","",C11/$C$52) -> 0.013586414
A12: =IF(B12="","",A11+1) -> 11 | B12: HCL TECHNOLOGIES LTD. | C12: 153 | D12: =IF(B12="", "", VLOOKUP(B12,'Raw Data'!$B$1:$C$701, 2, 0)) -> HCLTECH.NS | E12: =IF(B12="","",C12/$C$52) -> 0.030569431
A13: =IF(B13="","",A12+1) -> 12 | B13: HDFC BANK LTD | C13: 285 | D13: =IF(B13="", "", VLOOKUP(B13,'Raw Data'!$B$1:$C$701, 2, 0)) -> HDFCBANK.NS | E13: =IF(B13="","",C13/$C$52) -> 0.056943057
A14: =IF(B14="","",A13+1) -> 13 | B14: HDFC LIFE INSURANCE COMPANY LTD | C14: 81 | D14: =IF(B14="", "", VLOOKUP(B14,'Raw Data'!$B$1:$C$701, 2, 0)) -> HDFCLIFE.NS | E14: =IF(B14="","",C14/$C$52) -> 0.016183816
... A33: =IF(B33="","",A32+1) -> 32 | B33: V-MART RETAIL LTD. | C33: 74 | D33: =IF(B33="", "", VLOOKUP(B33,'Raw Data'!$B$1:$C$701, 2, 0)) -> VMART.NS | E33: =IF(B33="","",C33/$C$52) -> 0.014785215
A34: =IF(B34="","",A33+1) | D34: =IF(B34="", "", VLOOKUP(B34,'Raw Data'!$B$1:$C$701, 2, 0)) | E34: =IF(B34="","",C34/$C$52)
A35: =IF(B35="","",A34+1) | D35: =IF(B35="", "", VLOOKUP(B35,'Raw Data'!$B$1:$C$701, 2, 0)) | E35: =IF(B35="","",C35/$C$52)
A36: =IF(B36="","",A35+1) | D36: =IF(B36="", "", VLOOKUP(B36,'Raw Data'!$B$1:$C$701, 2, 0)) | E36: =IF(B36="","",C36/$C$52)
A37: =IF(B37="","",A36+1) | D37: =IF(B37="", "", VLOOKUP(B37,'Raw Data'!$B$1:$C$701, 2, 0)) | E37: =IF(B37="","",C37/$C$52)
A38: =IF(B38="","",A37+1) | D38: =IF(B38="", "", VLOOKUP(B38,'Raw Data'!$B$1:$C$701, 2, 0)) | E38: =IF(B38="","",C38/$C$52)
A39: =IF(B39="","",A38+1) | D39: =IF(B39="", "", VLOOKUP(B39,'Raw Data'!$B$1:$C$701, 2, 0)) | E39: =IF(B39="","",C39/$C$52)
A40: =IF(B40="","",A39+1) | D40: =IF(B40="", "", VLOOKUP(B40,'Raw Data'!$B$1:$C$701, 2, 0)) | E40: =IF(B40="","",C40/$C$52)
A41: =IF(B41="","",A40+1) | D41: =IF(B41="", "", VLOOKUP(B41,'Raw Data'!$B$1:$C$701, 2, 0)) | E41: =IF(B41="","",C41/$C$52)
A42: =IF(B42="","",A41+1) | D42: =IF(B42="", "", VLOOKUP(B42,'Raw Data'!$B$1:$C$701, 2, 0)) | E42: =IF(B42="","",C42/$C$52)
A43: =IF(B43="","",A42+1) | D43: =IF(B43="", "", VLOOKUP(B43,'Raw Data'!$B$1:$C$701, 2, 0)) | E43: =IF(B43="","",C43/$C$52)
A44: =IF(B44="","",A43+1) | D44: =IF(B44="", "", VLOOKUP(B44,'Raw Data'!$B$1:$C$701, 2, 0)) | E44: =IF(B44="","",C44/$C$52)
A45: =IF(B45="","",A44+1) | D45: =IF(B45="", "", VLOOKUP(B45,'Raw Data'!$B$1:$C$701, 2, 0)) | E45: =IF(B45="","",C45/$C$52)
... A51: =IF(B51="","",A50+1) | D51: =IF(B51="", "", VLOOKUP(B51,'Raw Data'!$B$1:$C$701, 2, 0)) | E51: =IF(B51="","",C51/$C$52)
A52: x | B52: x | C52: =SUM(C2:C51) -> 5005 | D52: x | E52: =C52/$C$52 -> 1

Sheet Raw Data
A1: Sr. No | B1: Company Name | C1: Ticker
A2: 1 | B2: 3M INDIA LTD. | C2: 3MINDIA.NS | F2: AJANTA PHARMA LTD. | H2: 71
A3: 2 | B3: AARTI DRUGS LTD. | C3: AARTIDRUGS.NS | F3: ASIAN PAINTS LTD. | H3: 178
A4: 3 | B4: AARTI INDUSTRIES LTD. | C4: AARTIIND.NS | F4: BANDHAN BANK LTD | H4: 203
A5: 4 | B5: AAVAS FINANCIERS LTD | C5: AAVAS.NS | F5: BLUE DART EXPRESS LTD. | H5: 33
A6: 5 | B6: ABB INDIA LIMITED | C6: ABB.NS | F6: CADILA HEALTHCARE LTD. | H6: 109
A7: 6 | B7: ABB POWER PRODUCTS AND SYSTEMS INDIA LTD | C7: POWERINDIA.NS | F7: CASTROL INDIA LTD. | H7: 116
A8: 7 | B8: ABBOTT INDIA LTD. | C8: ABBOTINDIA.NS | F8: CRISIL LTD. | H8: 145
A9: 8 | B9: ACC LTD. | C9: ACC.NS | F9: DIVI'S LABORATORIES LTD. | H9: 284
A10: 9 | B10: ACCELYA SOLUTIONS INDIA LTD | C10: ACCELYA.NS | F10: DR. LAL PATHLABS LTD | H10: 224
A11: 10 | B11: ACTION CONSTRUCTION EQUIPMENT LTD. | C11: ACE.NS | F11: EICHER MOTORS LTD. | H11: 68
A12: 11 | B12: ADANI ENTERPRISES LTD. | C12: ADANIENT.NS | F12: HCL TECHNOLOGIES LTD. | H12: 153
A13: 12 | B13: ADANI GREEN ENERGY LTD | C13: ADANIGREEN.NS | F13: HDFC BANK LTD | H13: 285
... A33: 32 | B33: ALLCARGO LOGISTICS LTD. | C33: ALLCARGO.NS | F33: V-MART RETAIL LTD. | H33: 74
A34: 33 | B34: AMARA RAJA BATTERIES LTD. | C34: AMARAJABAT.NS
A35: 34 | B35: AMBER ENTERPRISES INDIA LTD | C35: AMBER.NS
A36: 35 | B36: AMBUJA CEMENTS LTD. | C36: AMBUJACEM.NS
A37: 36 | B37: APAR INDUSTRIES LTD. | C37: APARINDS.NS
A38: 37 | B38: APCOTEX INDUSTRIES LTD. | C38: APCOTEXIND.NS
A39: 38 | B39: APEX FROZEN FOODS LTD | C39: APEX.NS
A40: 39 | B40: APL APOLLO TUBES LTD. | C40: APLAPOLLO.NS
A41: 40 | B41: APOLLO HOSPITALS ENTERPRISE LTD. | C41: APOLLOHOSP.NS
A42: 41 | B42: APOLLO PIPES LTD | C42: APOLLOPIPES.NS
A43: 42 | B43: APOLLO TRICOAT TUBES LTD | C43: APOLLOTRI.NS
A44: 43 | B44: APOLLO TYRES LTD. | C44: APOLLOTYRE.NS
A45: 44 | B45: APTECH LTD. | C45: APTECHT.NS
... A701: 700 | B701: ZYDUS WELLNESS LTD. | C701: ZYDUSWELL.NS

Sheet Analysis
B2: Orig | C2: New Value
B3: 50.05 | C3: =B3*1.47 -> 73.5735 | E3: assuming no trading
B5: Actuall
C6: 77.4
C7: 5.04 | D7: less - uti
C8: =C6-C7 -> 72.36
C9: 1.45 | D9: less uspl
C10: =C8-C9 -> 70.91
C11: =9.23-8.42 -> 0.81 | D11: add diff between sale and purch
C12: =C10+C11 -> 71.72 | E12: =C3-C12 -> 1.8535
F13: =E12/C3 -> 0.025192495

Sheet Sheet1
A1: Date | B1: Stock | C1: Action | D1: Qty | E1: Price | F1: Trade Value | G1: Order Ref. | H1: Settlement | I1: Segment | J1: DP Id - Client DP Id | K1: Exchange | L1: STT | M1: Transaction and SEBI Turnover charges | N1: Stamp Duty | O1: Brokerage + Service Tax | P1: Brokerage incl. taxes
A2: 44295 | B2: TATMOT | C2: Sell | D2: 20 | E2: 322.8 | F2: 6456 | G2: 20210409N200012221 | H2: 2021067 | I2: Rolling | J2: IN303028-51812720 | K2: NSE | L2: 6 | M2: 0.23 | N2: 0 | O2: 41.94 | P2: 48.166 | R2: =P2/F2 -> 0.0074606568
A3: 44294 | B3: TATMOT | C3: Sell | D3: 20 | E3: 312.5 | F3: 6250 | G3: 20210408N200010121 | H3: 2021066 | I3: Rolling | J3: IN303028-51812720 | K3: NSE | L3: 6.3 | M3: 0.22 | N3: 0 | O3: 41.34 | P3: 47.8588 | R3: =P3/F3 -> 0.007657408
A4: 44294 | B4: TATMOT | C4: Sell | D4: 20 | E4: 315 | F4: 6300 | G4: 20210408N200010269 | H4: 2021066 | I4: Rolling | J4: IN303028-51812720 | K4: NSE | L4: 6.3 | M4: 0.22 | N4: 0 | O4: 41.34 | P4: 47.8605 | R4: =P4/F4 -> 0.0075969048
A5: 44294 | B5: TATMOT | C5: Sell | D5: 20 | E5: 318.1 | F5: 6362 | G5: 20210408N200038727 | H5: 2021066 | I5: Rolling | J5: IN303028-51812720 | K5: NSE | L5: 6.39 | M5: 0.22 | N5: 0 | O5: 41.34 | P5: 47.9527 | R5: =P5/F5 -> 0.0075373625
A6: 44293 | B6: UTIAMC | C6: Sell | D6: 10 | E6: 585.1 | F6: 5851 | G6: 20210407N200044533 | H6: 2021065 | I6: Rolling | J6: IN303028-51812720 | K6: NSE | L6: 6 | M6: 0.2 | N6: 0 | O6: 41.34 | P6: 47.5448 | R6: =P6/F6 -> 0.0081259272
A7: 44291 | B7: TATMOT | C7: Sell | D7: 40 | E7: 306.3 | F7: 12252 | G7: 20210405N200014132 | H7: 2021063 | I7: Rolling | J7: IN303028-51812720 | K7: NSE | L7: 12 | M7: 0.43 | N7: 0 | O7: 79.6 | P7: 92.0288 | R7: =P7/F7 -> 0.0075113288
A8: 44287 | B8: TATMOT | C8: Sell | D8: 40 | E8: 305.7 | F8: 12228 | G8: 20210401N200009400 | H8: 2021062 | I8: Rolling | J8: IN303028-51812720 | K8: NSE | L8: 12.23 | M8: 0.43 | N8: 0 | O8: 79.44 | P8: 92.098 | R8: =P8/F8 -> 0.0075317305
A9: 44287 | B9: HDFSTA | C9: Buy | D9: 15 | E9: 686.05 | F9: 10290.75 | G9: 20210401N200009942 | H9: 2021062 | I9: Rolling | J9: IN303028-51812720 | K9: NSE | L9: 10.77 | M9: 0.36 | N9: 2 | O9: 66.85 | P9: 79.9802 | R9: =P9/F9 -> 0.0077720477
A10: 44285 | B10: CRISIL | C10: Buy | D10: 5 | E10: 1881 | F10: 9405 | G10: 20210330N200024779 | H10: 2021060 | I10: Rolling | J10: IN303028-51812720 | K10: NSE | L10: 9 | M10: 0.32 | N10: 1 | O10: 61.1 | P10: 71.4245 | R10: =P10/F10 -> 0.0075943115
A11: 44280 | B11: DABIND | C11: Buy | D11: 20 | E11: 521.75 | F11: 10435 | G11: 20210325N200036776 | H11: 2021058 | I11: Rolling | J11: IN303028-51812720 | K11: NSE | L11: 10.37 | M11: 0.36 | N11: 1.57 | O11: 67.79 | P11: 80.09 | R11: =P11/F11 -> 0.0076751318
A12: 44280 | B12: MARLIM | C12: Buy | D12: 25 | E12: 397 | F12: 9925 | G12: 20210325N200037438 | H12: 2021058 | I12: Rolling | J12: IN303028-51812720 | K12: NSE | L12: 9.93 | M12: 0.34 | N12: 1.49 | O12: 64.47 | P12: 76.2325 | R12: =P12/F12 -> 0.0076808564
A13: 44280 | B13: HDFSTA | C13: Buy | D13: 15 | E13: 666 | F13: 9990 | G13: 20210325N200038766 | H13: 2021058 | I13: Rolling | J13: IN303028-51812720 | K13: NSE | L13: 9.99 | M13: 0.34 | N13: 1.5 | O13: 64.9 | P13: 76.7347 | R13: =P13/F13 -> 0.0076811512
... A188: 43889 | B188: INDBA | C188: Buy | D188: 10 | E188: 1096 | F188: 10960 | G188: 20200228N200010119 | H188: 2020043 | I188: Rolling | J188: IN303028-51812720 | K188: NSE | L188: 11 | M188: 0.24 | N188: 2 | O188: 71.17 | P188: 84.4112 | R188: =P188/F188 -> 0.0077017518
F190: =SUMIF(C2:C188, "Buy", F2:F188) -> 842649.25 | P190: =SUM(P2:P188) -> 16147.227
F191: =SUMIF(C2:C188, "Sell", F2:F188) -> 1271111.1 | G191: =SUMIF(B2:B188, "UTIAMC", F2:F188) -> 347578.25 | H191: =F191-G191 -> 923532.9 | P191: =P190/(F191+F190) -> 0.0076390998
F193: =F191-F190 -> 428461.9

Sheet Sheet2
A3: Sum of Trade Value | B3: Column Labels
A4: Row Labels | B4: Buy | C4: Sell | D4: Grand Total
A5: ASIPAI | C5: 44310 | D5: 44310
A6: BLUDAR | B6: 21830 | D6: 21830
A7: BRIIND | B7: 17405 | D7: 17405
A8: CADHEA | C8: 37607.5 | D8: 37607.5
A9: CASIND | B9: 35887.5 | D9: 35887.5
A10: COLPAL | B10: 15310 | D10: 15310
A11: CRISIL | B11: 48602 | D11: 48602
A12: DABIND | B12: 170738 | D12: 170738
A13: DIVLAB | C13: 83889.15 | D13: 83889.15
A14: HDFAMC | B14: 147454.25 | D14: 147454.25
A15: HDFBAN | B15: 36155 | D15: 36155
A16: HDFSTA | B16: 32929.75 | D16: 32929.75
A17: INDBA | B17: 29941 | C17: 31494.5 | D17: 61435.5
A18: INFEDG | C18: 260223 | D18: 260223
A19: INFTEC | C19: 7050 | D19: 7050
A20: ITC | B20: 17430 | D20: 17430
A21: JUBFOO | C21: 248249.25 | D21: 248249.25
A22: LICHF | B22: 10517.5 | C22: 18000 | D22: 28517.5
A23: LTINFO | B23: 8110 | D23: 8110
A24: LUPIN | C24: 9490 | D24: 9490
A25: MARLIM | B25: 169424.75 | D25: 169424.75
A26: MOTSUM | B26: 9550 | C26: 30110 | D26: 39660
A27: PAGIND | B27: 33852 | D27: 33852
A28: SUNPHA | C28: 5390 | D28: 5390
A29: TATMOT | B29: 7520 | C29: 68035.5 | D29: 75555.5
A30: TCS | B30: 19742.5 | D30: 19742.5
A31: TITIND | B31: 10250 | C31: 7519.5 | D31: 17769.5
A32: UTIAMC | C32: 347578.25 | D32: 347578.25
A33: VMART | C33: 72164.5 | D33: 72164.5
A34: Grand Total | B34: 842649.25 | C34: 1271111.1 | D34: 2113760.4
