Workbook
Name stock_name: 'Raw Data'!$B$2:$B$701
Name ticker: 'Raw Data'!$C$2:$C$701

Sheet Portfolio
A1: sr-no | B1: company | C1: weight | D1: ticker | E1: normwt
A2: 1 | B2: HDFC BANK LTD | C2: 121 | D2: =IF(B2="", "", VLOOKUP(B2,'Raw Data'!$B$1:$C$701, 2, 0)) -> HDFCBANK.NS | E2: =IF(B2="","",C2/$C$52) -> 0.1602649
A3: =IF(B3="","",A2+1) -> 2 | B3: INFOSYS LTD. | C3: 122 | D3: =IF(B3="", "", VLOOKUP(B3,'Raw Data'!$B$1:$C$701, 2, 0)) -> INFY.NS | E3: =IF(B3="","",C3/$C$52) -> 0.1615894
A4: =IF(B4="","",A3+1) -> 3 | B4: ASIAN PAINTS LTD. | C4: 31 | D4: =IF(B4="", "", VLOOKUP(B4,'Raw Data'!$B$1:$C$701, 2, 0)) -> ASIANPAINT.NS | E4: =IF(B4="","",C4/$C$52) -> 0.041059603
A5: =IF(B5="","",A4+1) -> 4 | B5: SHREE CEMENT LTD. | C5: 20 | D5: =IF(B5="", "", VLOOKUP(B5,'Raw Data'!$B$1:$C$701, 2, 0)) -> SHREECEM.NS | E5: =IF(B5="","",C5/$C$52) -> 0.026490066
A6: =IF(B6="","",A5+1) -> 5 | B6: SUN PHARMACEUTICAL INDUSTRIES LTD. | C6: 99 | D6: =IF(B6="", "", VLOOKUP(B6,'Raw Data'!$B$1:$C$701, 2, 0)) -> SUNPHARMA.NS | E6: =IF(B6="","",C6/$C$52) -> 0.13112583
A7: =IF(B7="","",A6+1) -> 6 | B7: MARUTI SUZUKI INDIA LTD. | C7: 54 | D7: =IF(B7="", "", VLOOKUP(B7,'Raw Data'!$B$1:$C$701, 2, 0)) -> MARUTI.NS | E7: =IF(B7="","",C7/$C$52) -> 0.071523179
A8: =IF(B8="","",A7+1) -> 7 | B8: HERO MOTOCORP LTD. | C8: 32 | D8: =IF(B8="", "", VLOOKUP(B8,'Raw Data'!$B$1:$C$701, 2, 0)) -> HEROMOTOCO.NS | E8: =IF(B8="","",C8/$C$52) -> 0.042384106
A9: =IF(B9="","",A8+1) -> 8 | B9: ITC LTD. | C9: 77 | D9: =IF(B9="", "", VLOOKUP(B9,'Raw Data'!$B$1:$C$701, 2, 0)) -> ITC.NS | E9: =IF(B9="","",C9/$C$52) -> 0.10198675
A10: =IF(B10="","",A9+1) -> 9 | B10: LARSEN & TOUBRO LTD. | C10: 99 | D10: =IF(B10="", "", VLOOKUP(B10,'Raw Data'!$B$1:$C$701, 2, 0)) -> LT.NS | E10: =IF(B10="","",C10/$C$52) -> 0.13112583
A11: =IF(B11="","",A10+1) -> 10 | B11: TATA MOTORS LTD. | C11: 100 | D11: =IF(B11="", "", VLOOKUP(B11,'Raw Data'!$B$1:$C$701, 2, 0)) -> TATAMOTORS.NS | E11: =IF(B11="","",C11/$C$52) -> 0.13245033
A12: =IF(B12="","",A11+1) | D12: =IF(B12="", "", VLOOKUP(B12,'Raw Data'!$B$1:$C$701, 2, 0)) | E12: =IF(B12="","",C12/$C$52)
A13: =IF(B13="","",A12+1) | D13: =IF(B13="", "", VLOOKUP(B13,'Raw Data'!$B$1:$C$701, 2, 0)) | E13: =IF(B13="","",C13/$C$52)
A14: =IF(B14="","",A13+1) | D14: =IF(B14="", "", VLOOKUP(B14,'Raw Data'!$B$1:$C$701, 2, 0)) | E14: =IF(B14="","",C14/$C$52)
A15: =IF(B15="","",A14+1) | D15: =IF(B15="", "", VLOOKUP(B15,'Raw Data'!$B$1:$C$701, 2, 0)) | E15: =IF(B15="","",C15/$C$52)
A16: =IF(B16="","",A15+1) | D16: =IF(B16="", "", VLOOKUP(B16,'Raw Data'!$B$1:$C$701, 2, 0)) | E16: =IF(B16="","",C16/$C$52)
A17: =IF(B17="","",A16+1) | D17: =IF(B17="", "", VLOOKUP(B17,'Raw Data'!$B$1:$C$701, 2, 0)) | E17: =IF(B17="","",C17/$C$52)
A18: =IF(B18="","",A17+1) | D18: =IF(B18="", "", VLOOKUP(B18,'Raw Data'!$B$1:$C$701, 2, 0)) | E18: =IF(B18="","",C18/$C$52)
A19: =IF(B19="","",A18+1) | D19: =IF(B19="", "", VLOOKUP(B19,'Raw Data'!$B$1:$C$701, 2, 0)) | E19: =IF(B19="","",C19/$C$52)
A20: =IF(B20="","",A19+1) | D20: =IF(B20="", "", VLOOKUP(B20,'Raw Data'!$B$1:$C$701, 2, 0)) | E20: =IF(B20="","",C20/$C$52)
A21: =IF(B21="","",A20+1) | D21: =IF(B21="", "", VLOOKUP(B21,'Raw Data'!$B$1:$C$701, 2, 0)) | E21: =IF(B21="","",C21/$C$52)
A22: =IF(B22="","",A21+1) | D22: =IF(B22="", "", VLOOKUP(B22,'Raw Data'!$B$1:$C$701, 2, 0)) | E22: =IF(B22="","",C22/$C$52)
A23: =IF(B23="","",A22+1) | D23: =IF(B23="", "", VLOOKUP(B23,'Raw Data'!$B$1:$C$701, 2, 0)) | E23: =IF(B23="","",C23/$C$52)
... A51: =IF(B51="","",A50+1) | D51: =IF(B51="", "", VLOOKUP(B51,'Raw Data'!$B$1:$C$701, 2, 0)) | E51: =IF(B51="","",C51/$C$52)
A52: x | B52: x | C52: =SUM(C2:C51) -> 755 | D52: x | E52: =C52/$C$52 -> 1

Sheet Raw Data
A1: Sr. No | B1: Company Name | C1: Ticker
A2: 1 | B2: 3M INDIA LTD. | C2: 3MINDIA.NS
A3: 2 | B3: AARTI DRUGS LTD. | C3: AARTIDRUGS.NS
A4: 3 | B4: AARTI INDUSTRIES LTD. | C4: AARTIIND.NS
A5: 4 | B5: AAVAS FINANCIERS LTD | C5: AAVAS.NS
A6: 5 | B6: ABB INDIA LIMITED | C6: ABB.NS
A7: 6 | B7: ABB POWER PRODUCTS AND SYSTEMS INDIA LTD | C7: POWERINDIA.NS
A8: 7 | B8: ABBOTT INDIA LTD. | C8: ABBOTINDIA.NS
A9: 8 | B9: ACC LTD. | C9: ACC.NS
A10: 9 | B10: ACCELYA SOLUTIONS INDIA LTD | C10: ACCELYA.NS
A11: 10 | B11: ACTION CONSTRUCTION EQUIPMENT LTD. | C11: ACE.NS
A12: 11 | B12: ADANI ENTERPRISES LTD. | C12: ADANIENT.NS
A13: 12 | B13: ADANI GREEN ENERGY LTD | C13: ADANIGREEN.NS
... A700: 699 | B700: ZENSAR TECHNOLOGIES LTD. | C700: ZENSARTECH.NS
A701: 700 | B701: ZYDUS WELLNESS LTD. | C701: ZYDUSWELL.NS | D701: x

Sheet Sheet1
